mymathlib/__init__.py
mymathlib/calc.py
Toshikikuwae-0.1.0.dist-info/LICENSE
Toshikikuwae-0.1.0.dist-info/METADATA
Toshikikuwae-0.1.0.dist-info/WHEEL
Toshikikuwae-0.1.0.dist-info/top_level.txt
Toshikikuwae-0.1.0.dist-info/RECORD
