Metadata-Version: 2.1
Name: Toshikikuwae
Version: 0.1.0
Summary: A simple math library
Author: Your Name
Author-email: you@example.com
Classifier: Programming Language :: Python :: 3
Classifier: License :: OSI Approved :: MIT License
Classifier: Operating System :: OS Independent
Requires-Python: >=3.6
License-File: LICENSE
